{
  "collectionName": "components_shared_seos",
  "info": {
    "displayName": "SEO",
    "singularName": "seo",
    "pluralName": "seos",
    "description": "SEO component from @strapi/plugin-seo"
  },
  "options": {},
  "pluginOptions": {
    "i18n": {
      "localized": true
    }
  },
  "attributes": {
    "metaTitle": {
      "type": "string",
      "required": false,
      "maxLength": 255,
      "pluginOptions": {
        "i18n": {
          "localized": true
        }
      }
    },
    "metaDescription": {
      "type": "text",
      "required": false,
      "maxLength": 500,
      "pluginOptions": {
        "i18n": {
          "localized": true
        }
      }
    },
    "metaImage": {
      "type": "media",
      "multiple": false,
      "required": false,
      "allowedTypes": ["images"]
    },
    "keywords": {
      "type": "string",
      "required": false,
      "pluginOptions": {
        "i18n": {
          "localized": true
        }
      }
    },
    "metaRobots": {
      "type": "string",
      "required": false,
      "pluginOptions": {
        "i18n": {
          "localized": false
        }
      }
    },
    "structuredData": {
      "type": "json",
      "required": false,
      "pluginOptions": {
        "i18n": {
          "localized": false
        }
      }
    },
    "metaViewport": {
      "type": "string",
      "required": false,
      "pluginOptions": {
        "i18n": {
          "localized": false
        }
      }
    },
    "canonicalURL": {
      "type": "string",
      "required": false,
      "pluginOptions": {
        "i18n": {
          "localized": false
        }
      }
    }
  }
}
